cloud_sptheme/__init__.py
cloud_sptheme/make_helper.py
cloud_sptheme/utils.py
cloud_sptheme/ext/__init__.py
cloud_sptheme/ext/allow_unreferenced_footnotes.py
cloud_sptheme/ext/auto_redirect.py
cloud_sptheme/ext/autoattribute_search_bases.py
cloud_sptheme/ext/autodoc_sections.py
cloud_sptheme/ext/docfield_markup.py
cloud_sptheme/ext/escaped_samp_literals.py
cloud_sptheme/ext/index_styling.py
cloud_sptheme/ext/issue_tracker.py
cloud_sptheme/ext/page_only.py
cloud_sptheme/ext/perpage.py
cloud_sptheme/ext/relbar_links.py
cloud_sptheme/ext/relbar_toc.py
cloud_sptheme/ext/role_index.py
cloud_sptheme/ext/table_styling.py
cloud_sptheme/ext/static/auto_redirect.css
cloud_sptheme/ext/static/auto_redirect.html_t
cloud_sptheme/ext/static/table_styling.css
cloud_sptheme/tests/__init__.py
cloud_sptheme/tests/test_ext_relbar_toc.py
cloud_sptheme/tests/utils.py
cloud_sptheme/themes/cloud/globaltoc.html
cloud_sptheme/themes/cloud/layout.html
cloud_sptheme/themes/cloud/localtoc.html
cloud_sptheme/themes/cloud/quicklinks.html
cloud_sptheme/themes/cloud/relations.html
cloud_sptheme/themes/cloud/theme.conf
cloud_sptheme/themes/cloud/static/cloud.base.js
cloud_sptheme/themes/cloud/static/cloud.css_t
cloud_sptheme/themes/cloud/static/cloud.js_t
cloud_sptheme/themes/cloud/static/icon-caution.png
cloud_sptheme/themes/cloud/static/icon-danger.png
cloud_sptheme/themes/cloud/static/icon-deprecated.png
cloud_sptheme/themes/cloud/static/icon-note.png
cloud_sptheme/themes/cloud/static/icon-seealso.png
cloud_sptheme/themes/cloud/static/icon-todo.png
cloud_sptheme/themes/cloud/static/icon-warning.png
cloud_sptheme/themes/cloud/static/jquery.cookie.js
cloud_sptheme/themes/greencloud/theme.conf
cloud_sptheme/themes/magenta_cloud/theme.conf
cloud_sptheme/themes/redcloud/theme.conf
cloud_sptheme/themes/solarcloud/theme.conf
cloud_sptheme-1.10.1.post20200504175005.dist-info/LICENSE
cloud_sptheme-1.10.1.post20200504175005.dist-info/METADATA
cloud_sptheme-1.10.1.post20200504175005.dist-info/WHEEL
cloud_sptheme-1.10.1.post20200504175005.dist-info/entry_points.txt
cloud_sptheme-1.10.1.post20200504175005.dist-info/top_level.txt
cloud_sptheme-1.10.1.post20200504175005.dist-info/RECORD
