Metadata-Version: 1.1
Name: cloud-sptheme
Version: 1.10.1.post20200504175005
Summary: a nice sphinx theme named 'Cloud', and some related extensions
Home-page: https://cloud-sptheme.readthedocs.io
Author: Eli Collins
Author-email: elic@assurancetechnologies.com
License: BSD
Download-URL: https://pypi.python.org/pypi/cloud_sptheme
Keywords: sphinx extension theme
Platform: UNKNOWN
Classifier: Development Status :: 5 - Production/Stable
Classifier: Framework :: Sphinx :: Extension
Classifier: Framework :: Sphinx :: Theme
Classifier: Intended Audience :: Developers
Classifier: License :: OSI Approved :: BSD License
Classifier: Operating System :: OS Independent
Classifier: Programming Language :: Python :: 2.6
Classifier: Programming Language :: Python :: 2.7
Classifier: Programming Language :: Python :: 3
Classifier: Programming Language :: Python :: 3.3
Classifier: Programming Language :: Python :: 3.4
Classifier: Programming Language :: Python :: 3.5
Classifier: Programming Language :: Python :: 3.6
Classifier: Programming Language :: Python :: 3.7
Classifier: Programming Language :: Python :: 3.8
Classifier: Topic :: Documentation
Classifier: Topic :: Software Development :: Documentation
